{"packetCounter":"4264",
"datetime":"20230707 144354000",
"plateText":"\u0036\u0031\u0049\u0041\u004e",
"plateCountry":"No Country",
"ISO3166":{"Alpha3":"No Country"},
"plateConfidence":"0.606011",
"carState":"new",
"geotag":{"lat": 0,"lon": 0},"imageType": "frame","carMoveDirection":"unknown",
"timeProcessing":"0",
"timeDetection":"20230707 144354000",
"plateCoordinates":[829, 320, 257, 124],
"plateCoordinatesRelative":[829, 320, 257, 124],
"carID":"9361",
"datetimezone":"2023-07-07T14:43:-0500",
"carVerticalDirection":"unknown",
"camera_info":{"serialNumber":"ZR8N6V4W200006M","macAddress":"E430226AA341","cameraModel":"PNB-A9001LP"},
"channel":"1",
"recognitionZone":"1",
"imagesURI":["/home/setup/opensdk/html/WisenetRoadAI/images/images/20230707134125_871606/20230707144356_148700lp_61IAN.png","/home/setup/opensdk/html/WisenetRoadAI/images/images/20230707134125_871606/20230707144356_148700.jpeg","/home/setup/opensdk/html/WisenetRoadAI/images/images/20230707134125_871606/20230707144356_148700lp_61IAN.jpeg"],
"plateASCII":"61IAN",
"plateUnicode":"\u0036\u0031\u0049\u0041\u004e",
"vehicle_info":{"brand":"Mazda","model":"CX","type":"SUV","color":"GRAY","confidenceColor":"0.000000","confidenceMMR":"0.490175","coordinates":[444, 0, 1024, 818]},
"sensorProviderID":"LPR_ALTO",
"capture_timestamp":"1688741034517",
"frame_timestamp":"1688741034517"
}