{"packetCounter":"4051",
"datetime":"20230629 234728000",
"plateText":"\u0050\u0049\u0051\u0032\u0035\u0030",
"plateCountry":"PRY",
"ISO3166":{"Alpha3":"PRY"},
"plateConfidence":"0.624129",
"carState":"new",
"geotag":{"lat": 0,"lon": 0},"imageType": "frame","carMoveDirection":"unknown",
"timeProcessing":"0",
"timeDetection":"20230629 234728000",
"plateCoordinates":[1309, 352, 94, 40],
"plateCoordinatesRelative":[1309, 352, 94, 40],
"carID":"4052",
"datetimezone":"2023-06-29T23:47:-0500",
"carVerticalDirection":"unknown",
"camera_info":{"serialNumber":"ZR8N6V4W200006M","macAddress":"E430226AA341","cameraModel":"PNB-A9001LP"},
"channel":"1",
"recognitionZone":"1",
"imagesURI":["/home/setup/opensdk/html/WisenetRoadAI/images/images/20230629230740_607949/20230629234736_154998lp_PIQ250.png","/home/setup/opensdk/html/WisenetRoadAI/images/images/20230629230740_607949/20230629234736_154998.jpeg","/home/setup/opensdk/html/WisenetRoadAI/images/images/20230629230740_607949/20230629234736_154998lp_PIQ250.jpeg"],
"plateASCII":"PIQ250",
"plateUnicode":"\u0050\u0049\u0051\u0032\u0035\u0030",
"vehicle_info":{"brand":"Citroen","model":"c4/elysee","type":"CAR","color":"NONE","confidenceColor":"0.000000","confidenceMMR":"0.330583","coordinates":[1168, 0, 376, 512]},
"sensorProviderID":"LPR_ALTO",
"capture_timestamp":"1688082448867",
"frame_timestamp":"1688082448867"
}