{"ISO3166":{"Alpha3":"PER"},"camera_info":{"cameraModel":"PNB-A9001LP","macAddress":"E430226AA341","serialNumber":"ZR8N6V4W200006M"},"capture_timestamp":1689256663515,"carID":12496,"carMoveDirection":"unknown","carState":"new","carVerticalDirection":"unknown","channel":"1","datetime":"20230713 135743000","datetimezone":"2023-07-13T13:57:-0500","frame_timestamp":1689256663515,"geotag":{"lat":0.0,"lon":0.0},"imageType":"frame","imagesURI":["/home/setup/opensdk/html/WisenetRoadAI/images/images/20230713135500_15231/20230713135744_222554lp_P2X638.png","/home/setup/opensdk/html/WisenetRoadAI/images/images/20230713135500_15231/20230713135744_222554.jpeg","/home/setup/opensdk/html/WisenetRoadAI/images/images/20230713135500_15231/20230713135744_222554lp_P2X638.jpeg"],"packetCounter":0,"plateASCII":"P2X638","plateConfidence":0.660838782787323,"plateCoordinates":[2910,1090,468,164],"plateCoordinatesRelative":[2910,1090,468,164],"plateCountry":"PER","plateText":"\\u0050\\u0032\\u0058\\u0036\\u0033\\u0038","plateUnicode":"\\u0050\\u0032\\u0058\\u0036\\u0033\\u0038","recognitionZone":1,"sensorProviderID":"LPR_ALTO","timeDetection":1689256663515,"timeProcessing":0,"vehicle_info":{"brand":"","color":"","confidenceColor":0.0,"confidenceMMR":0.0,"coordinates":[1104,0,936,872],"model":"","type":""}}