{"packetCounter":"463",
"datetime":"20230523 182709000",
"plateText":"\u0049\u0030\u0031\u0050\u004f\u0054\u0038\u0049",
"plateCountry":"No Country",
"ISO3166":{"Alpha3":"No Country"},
"plateConfidence":"0.644183",
"carState":"new",
"geotag":{"lat": -12.58898,"lon": -76.56886},"imageType": "frame","carMoveDirection":"unknown",
"timeProcessing":"0",
"timeDetection":"20230523 182709000",
"plateCoordinates":[1065, 813, 195, 62],
"plateCoordinatesRelative":[1065, 813, 195, 62],
"carID":"22992",
"datetimezone":"2023-05-23T18:27:-0500",
"carVerticalDirection":"unknown",
"camera_info":{"serialNumber":"ZR8N6V4W20000AP","macAddress":"E430226AA345","cameraModel":"PNB-A9001LP"},
"channel":"1",
"recognitionZone":"1",
"imagesURI":["/home/setup/opensdk/html/WisenetRoadAI/images/images/20230523175020_772691/20230523182710_204477lp_I01POT8I.png","/home/setup/opensdk/html/WisenetRoadAI/images/images/20230523175020_772691/20230523182710_204477.jpeg","/home/setup/opensdk/html/WisenetRoadAI/images/images/20230523175020_772691/20230523182710_204477lp_I01POT8I.jpeg"],
"plateASCII":"I01POT8I",
"plateUnicode":"\u0049\u0030\u0031\u0050\u004f\u0054\u0038\u0049",
"vehicle_info":{"brand":"(None)","model":"","type":"UNDEFINED","color":"GRAY","confidenceColor":"0.000000","confidenceMMR":"0.168387","coordinates":[772, 68, 776, 995]},
"sensorProviderID":"LPR_OFICINA",
"capture_timestamp":"1684866429272",
"frame_timestamp":"1684866429272"
}