{"packetCounter":"971",
"datetime":"20230523 192014000",
"plateText":"\u004f\u0030\u0030\u0035\u0030\u0030",
"plateCountry":"COL",
"ISO3166":{"Alpha3":"COL"},
"plateConfidence":"0.839297",
"carState":"new",
"geotag":{"lat": -12.58898,"lon": -76.56886},"imageType": "frame","carMoveDirection":"unknown",
"timeProcessing":"0",
"timeDetection":"20230523 192014000",
"plateCoordinates":[534, 658, 118, 40],
"plateCoordinatesRelative":[534, 658, 118, 40],
"carID":"23509",
"datetimezone":"2023-05-23T19:20:-0500",
"carVerticalDirection":"unknown",
"camera_info":{"serialNumber":"ZR8N6V4W20000AP","macAddress":"E430226AA345","cameraModel":"PNB-A9001LP"},
"channel":"1",
"recognitionZone":"1",
"imagesURI":["/home/setup/opensdk/html/WisenetRoadAI/images/images/20230523191034_749989/20230523192015_455073lp_O00500.png","/home/setup/opensdk/html/WisenetRoadAI/images/images/20230523191034_749989/20230523192015_455073.jpeg","/home/setup/opensdk/html/WisenetRoadAI/images/images/20230523191034_749989/20230523192015_455073lp_O00500.jpeg"],
"plateASCII":"O00500",
"plateUnicode":"\u004f\u0030\u0030\u0035\u0030\u0030",
"vehicle_info":{"brand":"Freightliner","model":"MT","type":"LCV","color":"WHITE","confidenceColor":"0.000000","confidenceMMR":"0.399834","coordinates":[356, 178, 472, 640]},
"sensorProviderID":"LPR_OFICINA",
"capture_timestamp":"1684869614648",
"frame_timestamp":"1684869614648"
}