{"packetCounter":"4069",
"datetime":"20230630 000325000",
"plateText":"\u0050\u0059\u0037\u0036\u0032",
"plateCountry":"CHL",
"ISO3166":{"Alpha3":"CHL"},
"plateConfidence":"0.715092",
"carState":"new",
"geotag":{"lat": 0,"lon": 0},"imageType": "frame","carMoveDirection":"unknown",
"timeProcessing":"0",
"timeDetection":"20230630 000325000",
"plateCoordinates":[1192, 265, 89, 33],
"plateCoordinatesRelative":[1192, 265, 89, 33],
"carID":"4070",
"datetimezone":"2023-06-30T00:03:-0500",
"carVerticalDirection":"unknown",
"camera_info":{"serialNumber":"ZR8N6V4W200006M","macAddress":"E430226AA341","cameraModel":"PNB-A9001LP"},
"channel":"1",
"recognitionZone":"1",
"imagesURI":["/home/setup/opensdk/html/WisenetRoadAI/images/images/20230629230740_607949/20230630000326_360410lp_PY762.png","/home/setup/opensdk/html/WisenetRoadAI/images/images/20230629230740_607949/20230630000326_360410.jpeg","/home/setup/opensdk/html/WisenetRoadAI/images/images/20230629230740_607949/20230630000326_360410lp_PY762.jpeg"],
"plateASCII":"PY762",
"plateUnicode":"\u0050\u0059\u0037\u0036\u0032",
"vehicle_info":{"brand":"(None)","model":"","type":"UNDEFINED","color":"NONE","confidenceColor":"0.000000","confidenceMMR":"0.218775","coordinates":[1056, 0, 352, 399]},
"sensorProviderID":"LPR_ALTO",
"capture_timestamp":"1688083405960",
"frame_timestamp":"1688083405960"
}