{"packetCounter":"4204",
"datetime":"20230630 050602000",
"plateText":"\u0050\u0042\u004b\u0032\u0038\u0037",
"plateCountry":"COL",
"ISO3166":{"Alpha3":"COL"},
"plateConfidence":"0.707866",
"carState":"new",
"geotag":{"lat": 0,"lon": 0},"imageType": "frame","carMoveDirection":"unknown",
"timeProcessing":"0",
"timeDetection":"20230630 050602000",
"plateCoordinates":[1342, 692, 117, 48],
"plateCoordinatesRelative":[1342, 692, 117, 48],
"carID":"4205",
"datetimezone":"2023-06-30T05:06:-0500",
"carVerticalDirection":"unknown",
"camera_info":{"serialNumber":"ZR8N6V4W200006M","macAddress":"E430226AA341","cameraModel":"PNB-A9001LP"},
"channel":"1",
"recognitionZone":"1",
"imagesURI":["/home/setup/opensdk/html/WisenetRoadAI/images/images/20230630050122_190666/20230630050602_998265lp_PBK287.png","/home/setup/opensdk/html/WisenetRoadAI/images/images/20230630050122_190666/20230630050602_998265.jpeg","/home/setup/opensdk/html/WisenetRoadAI/images/images/20230630050122_190666/20230630050602_998265lp_PBK287.jpeg"],
"plateASCII":"PBK287",
"plateUnicode":"\u0050\u0042\u004b\u0032\u0038\u0037",
"vehicle_info":{"brand":"(None)","model":"","type":"UNDEFINED","color":"NONE","confidenceColor":"0.000000","confidenceMMR":"0.098484","coordinates":[1164, 116, 464, 772]},
"sensorProviderID":"LPR_ALTO",
"capture_timestamp":"1688101562609",
"frame_timestamp":"1688101562609"
}