{"packetCounter":"570",
"datetime":"20230625 125650000",
"plateText":"\u0041\u0042\u0038\u0039\u0038\u0030",
"plateCountry":"BRA",
"ISO3166":{"Alpha3":"BRA"},
"plateConfidence":"0.690897",
"carState":"new",
"geotag":{"lat": 0,"lon": 0},"imageType": "frame","carMoveDirection":"unknown",
"timeProcessing":"0",
"timeDetection":"20230625 125650000",
"plateCoordinates":[1130, 280, 77, 42],
"plateCoordinatesRelative":[1130, 280, 77, 42],
"carID":"571",
"datetimezone":"2023-06-25T12:56:-0500",
"carVerticalDirection":"unknown",
"camera_info":{"serialNumber":"ZR8N6V4W200006M","macAddress":"E430226AA341","cameraModel":"PNB-A9001LP"},
"channel":"1",
"recognitionZone":"1",
"imagesURI":["/home/setup/opensdk/html/WisenetRoadAI/images/images/20230625044524_938286/20230625125651_634768lp_AB8980.png","/home/setup/opensdk/html/WisenetRoadAI/images/images/20230625044524_938286/20230625125651_634768.jpeg","/home/setup/opensdk/html/WisenetRoadAI/images/images/20230625044524_938286/20230625125651_634768lp_AB8980.jpeg"],
"plateASCII":"AB8980",
"plateUnicode":"\u0041\u0042\u0038\u0039\u0038\u0030",
"vehicle_info":{"brand":"Volkswagen","model":"Beetle","type":"CAR","color":"BEIGE","confidenceColor":"0.000000","confidenceMMR":"0.998619","coordinates":[1012, 0, 304, 452]},
"sensorProviderID":"ID_ALTO_LPR",
"capture_timestamp":"1687697810900",
"frame_timestamp":"1687697810900"
}