{"packetCounter":"5299",
"datetime":"20230614 212213000",
"plateText":"\u0042\u0042\u0053\u0038\u0036\u0035",
"plateCountry":"PRY",
"ISO3166":{"Alpha3":"PRY"},
"plateConfidence":"0.738086",
"carState":"new",
"geotag":{"lat": -12.58898,"lon": -76.56886},"imageType": "frame","carMoveDirection":"unknown",
"timeProcessing":"0",
"timeDetection":"20230614 212213000",
"plateCoordinates":[1213, 37, 111, 44],
"plateCoordinatesRelative":[1213, 37, 111, 44],
"carID":"12497",
"datetimezone":"2023-06-14T21:22:+0000",
"carVerticalDirection":"unknown",
"camera_info":{"serialNumber":"ZR8N6V4W200006M","macAddress":"E430226AA341","cameraModel":"PNB-A9001LP"},
"channel":"1",
"recognitionZone":"1",
"imagesURI":["/home/setup/opensdk/html/WisenetRoadAI/images/images/20230614192741_737978/20230614212213_286774lp_BBS865.png","/home/setup/opensdk/html/WisenetRoadAI/images/images/20230614192741_737978/20230614212213_286774.jpeg","/home/setup/opensdk/html/WisenetRoadAI/images/images/20230614192741_737978/20230614212213_286774lp_BBS865.jpeg"],
"plateASCII":"BBS865",
"plateUnicode":"\u0042\u0042\u0053\u0038\u0036\u0035",
"vehicle_info":{"brand":"Undefined","model":"","type":"BUS","color":"NONE","confidenceColor":"0.000000","confidenceMMR":"0.860652","coordinates":[1044, 0, 440, 213]},
"sensorProviderID":"ID_ALTO_LPR",
"capture_timestamp":"1686777733008",
"frame_timestamp":"1686777733008"
}