{"packetCounter":"5231",
"datetime":"20230708 194833000",
"plateText":"\u0054\u0042\u0053\u0038\u0035\u0032\u0031",
"plateCountry":"URY",
"ISO3166":{"Alpha3":"URY"},
"plateConfidence":"0.768886",
"carState":"new",
"geotag":{"lat": 0,"lon": 0},"imageType": "frame","carMoveDirection":"unknown",
"timeProcessing":"0",
"timeDetection":"20230708 194833000",
"plateCoordinates":[1212, 258, 92, 40],
"plateCoordinatesRelative":[1212, 258, 92, 40],
"carID":"10328",
"datetimezone":"2023-07-08T19:48:-0500",
"carVerticalDirection":"unknown",
"camera_info":{"serialNumber":"ZR8N6V4W200006M","macAddress":"E430226AA341","cameraModel":"PNB-A9001LP"},
"channel":"1",
"recognitionZone":"1",
"imagesURI":["/home/setup/opensdk/html/WisenetRoadAI/images/images/20230708185736_378635/20230708194833_991307lp_TBS8521.png","/home/setup/opensdk/html/WisenetRoadAI/images/images/20230708185736_378635/20230708194833_991307.jpeg","/home/setup/opensdk/html/WisenetRoadAI/images/images/20230708185736_378635/20230708194833_991307lp_TBS8521.jpeg"],
"plateASCII":"TBS8521",
"plateUnicode":"\u0054\u0042\u0053\u0038\u0035\u0032\u0031",
"vehicle_info":{"brand":"Toyota","model":"Hiace","type":"LCV","color":"WHITE","confidenceColor":"0.000000","confidenceMMR":"0.506274","coordinates":[1072, 0, 368, 418]},
"sensorProviderID":"LPR_ALTO",
"capture_timestamp":"1688845713394",
"frame_timestamp":"1688845713394"
}