{"packetCounter":"236",
"datetime":"20230523 155214000",
"plateText":"\u0032\u0033\u0054\u0031\u0035\u004f\u0037\u0034\u0038\u0038\u0036",
"plateCountry":"No Country",
"ISO3166":{"Alpha3":"No Country"},
"plateConfidence":"0.717740",
"carState":"new",
"geotag":{"lat": -12.58898,"lon": -76.56886},"imageType": "frame","carMoveDirection":"out",
"timeProcessing":"0",
"timeDetection":"20230523 155214000",
"plateCoordinates":[2277, 1291, 357, 66],
"plateCoordinatesRelative":[2277, 1291, 357, 66],
"carID":"21259",
"datetimezone":"2023-05-23T15:52:-0500",
"carVerticalDirection":"down",
"camera_info":{"serialNumber":"ZR8N6V4W20000AP","macAddress":"E430226AA345","cameraModel":"PNB-A9001LP"},
"channel":"1",
"recognitionZone":"1",
"imagesURI":["/home/setup/opensdk/html/WisenetRoadAI/images/images/20230523153042_480710/20230523155217_246897lp_23T15O74886.png","/home/setup/opensdk/html/WisenetRoadAI/images/images/20230523153042_480710/20230523155217_246897.jpeg","/home/setup/opensdk/html/WisenetRoadAI/images/images/20230523153042_480710/20230523155217_246897lp_23T15O74886.jpeg"],
"plateASCII":"23T15O74886",
"plateUnicode":"\u0032\u0033\u0054\u0031\u0035\u004f\u0037\u0034\u0038\u0038\u0036",
"vehicle_info":{"brand":"Undefined","model":"","type":"BUS","color":"NONE","confidenceColor":"0.000000","confidenceMMR":"0.716093","coordinates":[1740, 498, 1424, 1058]},
"sensorProviderID":"LPR_OFICINA",
"capture_timestamp":"1684857134934",
"frame_timestamp":"1684857134934"
}