{"packetCounter":"2362",
"datetime":"20230627 224107000",
"plateText":"\u0050\u0049\u0046\u0037\u0034\u0036",
"plateCountry":"PRY",
"ISO3166":{"Alpha3":"PRY"},
"plateConfidence":"0.656743",
"carState":"new",
"geotag":{"lat": 0,"lon": 0},"imageType": "frame","carMoveDirection":"unknown",
"timeProcessing":"0",
"timeDetection":"20230627 224107000",
"plateCoordinates":[1103, 340, 91, 42],
"plateCoordinatesRelative":[1103, 340, 91, 42],
"carID":"2363",
"datetimezone":"2023-06-27T22:41:-0500",
"carVerticalDirection":"unknown",
"camera_info":{"serialNumber":"ZR8N6V4W200006M","macAddress":"E430226AA341","cameraModel":"PNB-A9001LP"},
"channel":"1",
"recognitionZone":"1",
"imagesURI":["/home/setup/opensdk/html/WisenetRoadAI/images/images/20230627211955_489687/20230627224107_402253lp_PIF746.png","/home/setup/opensdk/html/WisenetRoadAI/images/images/20230627211955_489687/20230627224107_402253.jpeg","/home/setup/opensdk/html/WisenetRoadAI/images/images/20230627211955_489687/20230627224107_402253lp_PIF746.jpeg"],
"plateASCII":"PIF746",
"plateUnicode":"\u0050\u0049\u0046\u0037\u0034\u0036",
"vehicle_info":{"brand":"(None)","model":"","type":"UNDEFINED","color":"WHITE","confidenceColor":"0.000000","confidenceMMR":"0.175551","coordinates":[964, 0, 360, 512]},
"sensorProviderID":"LPR_ALTO",
"capture_timestamp":"1687905667077",
"frame_timestamp":"1687905667077"
}