{"packetCounter":"858",
"datetime":"20230523 060113000",
"plateText":"\u004d\u0038\u0049\u0050\u0038\u0055",
"plateCountry":"No Country",
"ISO3166":{"Alpha3":"No Country"},
"plateConfidence":"0.620461",
"carState":"new",
"geotag":{"lat": -12.58898,"lon": -76.56886},"imageType": "frame","carMoveDirection":"unknown",
"timeProcessing":"0",
"timeDetection":"20230523 060113000",
"plateCoordinates":[1514, 1553, 273, 132],
"plateCoordinatesRelative":[1514, 1553, 273, 132],
"carID":"19721",
"datetimezone":"2023-05-23T06:01:-0500",
"carVerticalDirection":"unknown",
"camera_info":{"serialNumber":"ZR8N6V4W20000AP","macAddress":"E430226AA345","cameraModel":"PNB-A9001LP"},
"channel":"1",
"recognitionZone":"2",
"imagesURI":["/home/setup/opensdk/html/WisenetRoadAI/images/images/20230523055859_280451/20230523060115_10231lp_M8IP8U.png","/home/setup/opensdk/html/WisenetRoadAI/images/images/20230523055859_280451/20230523060115_10231.jpeg","/home/setup/opensdk/html/WisenetRoadAI/images/images/20230523055859_280451/20230523060115_10231lp_M8IP8U.jpeg"],
"plateASCII":"M8IP8U",
"plateUnicode":"\u004d\u0038\u0049\u0050\u0038\u0055",
"vehicle_info":{"brand":"(None)","model":"","type":"UNDEFINED","color":"NONE","confidenceColor":"0.000000","confidenceMMR":"0.167517","coordinates":[1104, 0, 1088, 2085]},
"sensorProviderID":"LPR_OFICINA",
"capture_timestamp":"1684821673399",
"frame_timestamp":"1684821673399"
}