{"packetCounter":"4164",
"datetime":"20230630 030016000",
"plateText":"\u0050\u0033\u0036\u0038\u0039\u0037",
"plateCountry":"No Country",
"ISO3166":{"Alpha3":"No Country"},
"plateConfidence":"0.667230",
"carState":"new",
"geotag":{"lat": 0,"lon": 0},"imageType": "frame","carMoveDirection":"unknown",
"timeProcessing":"0",
"timeDetection":"20230630 030016000",
"plateCoordinates":[1241, 271, 107, 26],
"plateCoordinatesRelative":[1241, 271, 107, 26],
"carID":"4165",
"datetimezone":"2023-06-30T03:00:-0500",
"carVerticalDirection":"unknown",
"camera_info":{"serialNumber":"ZR8N6V4W200006M","macAddress":"E430226AA341","cameraModel":"PNB-A9001LP"},
"channel":"1",
"recognitionZone":"1",
"imagesURI":["/home/setup/opensdk/html/WisenetRoadAI/images/images/20230630003541_327606/20230630030017_288377lp_P36897.png","/home/setup/opensdk/html/WisenetRoadAI/images/images/20230630003541_327606/20230630030017_288377.jpeg","/home/setup/opensdk/html/WisenetRoadAI/images/images/20230630003541_327606/20230630030017_288377lp_P36897.jpeg"],
"plateASCII":"P36897",
"plateUnicode":"\u0050\u0033\u0036\u0038\u0039\u0037",
"vehicle_info":{"brand":"(None)","model":"","type":"UNDEFINED","color":"NONE","confidenceColor":"0.000000","confidenceMMR":"0.110330","coordinates":[1080, 0, 424, 376]},
"sensorProviderID":"LPR_ALTO",
"capture_timestamp":"1688094016975",
"frame_timestamp":"1688094016975"
}