{"packetCounter":"4199",
"datetime":"20230630 050049000",
"plateText":"\u0036\u0056\u0033\u0038\u0033",
"plateCountry":"No Country",
"ISO3166":{"Alpha3":"No Country"},
"plateConfidence":"0.626940",
"carState":"new",
"geotag":{"lat": 0,"lon": 0},"imageType": "frame","carMoveDirection":"unknown",
"timeProcessing":"0",
"timeDetection":"20230630 050049000",
"plateCoordinates":[1432, 908, 161, 44],
"plateCoordinatesRelative":[1432, 908, 161, 44],
"carID":"4200",
"datetimezone":"2023-06-30T05:00:-0500",
"carVerticalDirection":"unknown",
"camera_info":{"serialNumber":"ZR8N6V4W200006M","macAddress":"E430226AA341","cameraModel":"PNB-A9001LP"},
"channel":"1",
"recognitionZone":"1",
"imagesURI":["/home/setup/opensdk/html/WisenetRoadAI/images/images/20230630003541_327606/20230630050050_161915lp_6V383.png","/home/setup/opensdk/html/WisenetRoadAI/images/images/20230630003541_327606/20230630050050_161915.jpeg","/home/setup/opensdk/html/WisenetRoadAI/images/images/20230630003541_327606/20230630050050_161915lp_6V383.jpeg"],
"plateASCII":"6V383",
"plateUnicode":"\u0036\u0056\u0033\u0038\u0033",
"vehicle_info":{"brand":"Citroen","model":"c4/elysee","type":"CAR","color":"NONE","confidenceColor":"0.000000","confidenceMMR":"0.475288","coordinates":[1188, 380, 640, 703]},
"sensorProviderID":"LPR_ALTO",
"capture_timestamp":"1688101249721",
"frame_timestamp":"1688101249721"
}