{"packetCounter":"769",
"datetime":"20230625 190551000",
"plateText":"\u0042\u004b\u0050\u0035\u0030\u0036",
"plateCountry":"PRY",
"ISO3166":{"Alpha3":"PRY"},
"plateConfidence":"0.773464",
"carState":"new",
"geotag":{"lat": 0,"lon": 0},"imageType": "frame","carMoveDirection":"unknown",
"timeProcessing":"0",
"timeDetection":"20230625 190551000",
"plateCoordinates":[735, 282, 88, 40],
"plateCoordinatesRelative":[735, 282, 88, 40],
"carID":"770",
"datetimezone":"2023-06-25T19:05:-0500",
"carVerticalDirection":"unknown",
"camera_info":{"serialNumber":"ZR8N6V4W200006M","macAddress":"E430226AA341","cameraModel":"PNB-A9001LP"},
"channel":"1",
"recognitionZone":"1",
"imagesURI":["/home/setup/opensdk/html/WisenetRoadAI/images/images/20230625171818_365189/20230625190552_299056lp_BKP506.png","/home/setup/opensdk/html/WisenetRoadAI/images/images/20230625171818_365189/20230625190552_299056.jpeg","/home/setup/opensdk/html/WisenetRoadAI/images/images/20230625171818_365189/20230625190552_299056lp_BKP506.jpeg"],
"plateASCII":"BKP506",
"plateUnicode":"\u0042\u004b\u0050\u0035\u0030\u0036",
"vehicle_info":{"brand":"Honda","model":"Jazz","type":"CAR","color":"BLUE","confidenceColor":"0.000000","confidenceMMR":"0.703129","coordinates":[600, 0, 352, 442]},
"sensorProviderID":"ID_ALTO_LPR",
"capture_timestamp":"1687719951639",
"frame_timestamp":"1687719951639"
}