{"packetCounter":"4801",
"datetime":"20230708 004422000",
"plateText":"\u0041\u0046\u0053\u0034\u0035\u0039",
"plateCountry":"PRY",
"ISO3166":{"Alpha3":"PRY"},
"plateConfidence":"0.773901",
"carState":"new",
"geotag":{"lat": 0,"lon": 0},"imageType": "frame","carMoveDirection":"unknown",
"timeProcessing":"0",
"timeDetection":"20230708 004422000",
"plateCoordinates":[1216, 272, 90, 36],
"plateCoordinatesRelative":[1216, 272, 90, 36],
"carID":"9898",
"datetimezone":"2023-07-08T00:44:-0500",
"carVerticalDirection":"unknown",
"camera_info":{"serialNumber":"ZR8N6V4W200006M","macAddress":"E430226AA341","cameraModel":"PNB-A9001LP"},
"channel":"1",
"recognitionZone":"1",
"imagesURI":["/home/setup/opensdk/html/WisenetRoadAI/images/images/20230708004120_319975/20230708004422_404720lp_AFS459.png","/home/setup/opensdk/html/WisenetRoadAI/images/images/20230708004120_319975/20230708004422_404720.jpeg","/home/setup/opensdk/html/WisenetRoadAI/images/images/20230708004120_319975/20230708004422_404720lp_AFS459.jpeg"],
"plateASCII":"AFS459",
"plateUnicode":"\u0041\u0046\u0053\u0034\u0035\u0039",
"vehicle_info":{"brand":"Kia","model":"Carnival","type":"CAR","color":"NONE","confidenceColor":"0.000000","confidenceMMR":"0.327650","coordinates":[1080, 0, 360, 416]},
"sensorProviderID":"LPR_ALTO",
"capture_timestamp":"1688777062061",
"frame_timestamp":"1688777062061"
}