{"packetCounter":"4116",
"datetime":"20230707 110212000",
"plateText":"\u0050\u0049\u0042\u0034\u0035\u0031",
"plateCountry":"PRY",
"ISO3166":{"Alpha3":"PRY"},
"plateConfidence":"0.610116",
"carState":"new",
"geotag":{"lat": 0,"lon": 0},"imageType": "frame","carMoveDirection":"unknown",
"timeProcessing":"0",
"timeDetection":"20230707 110212000",
"plateCoordinates":[1141, 330, 94, 42],
"plateCoordinatesRelative":[1141, 330, 94, 42],
"carID":"9213",
"datetimezone":"2023-07-07T11:02:-0500",
"carVerticalDirection":"unknown",
"camera_info":{"serialNumber":"ZR8N6V4W200006M","macAddress":"E430226AA341","cameraModel":"PNB-A9001LP"},
"channel":"1",
"recognitionZone":"1",
"imagesURI":["/home/setup/opensdk/html/WisenetRoadAI/images/images/20230707060444_728873/20230707110212_752213lp_PIB451.png","/home/setup/opensdk/html/WisenetRoadAI/images/images/20230707060444_728873/20230707110212_752213.jpeg","/home/setup/opensdk/html/WisenetRoadAI/images/images/20230707060444_728873/20230707110212_752213lp_PIB451.jpeg"],
"plateASCII":"PIB451",
"plateUnicode":"\u0050\u0049\u0042\u0034\u0035\u0031",
"vehicle_info":{"brand":"(None)","model":"","type":"UNDEFINED","color":"NONE","confidenceColor":"0.000000","confidenceMMR":"0.279103","coordinates":[1000, 0, 376, 498]},
"sensorProviderID":"LPR_ALTO",
"capture_timestamp":"1688727732311",
"frame_timestamp":"1688727732311"
}