{"packetCounter":"1211",
"datetime":"20230523 062328000",
"plateText":"\u0030\u0038\u0052\u0030\u0043\u0038\u004a\u0045",
"plateCountry":"No Country",
"ISO3166":{"Alpha3":"No Country"},
"plateConfidence":"0.627589",
"carState":"new",
"geotag":{"lat": -12.58898,"lon": -76.56886},"imageType": "frame","carMoveDirection":"unknown",
"timeProcessing":"0",
"timeDetection":"20230523 062328000",
"plateCoordinates":[1354, 1730, 405, 72],
"plateCoordinatesRelative":[1354, 1730, 405, 72],
"carID":"20106",
"datetimezone":"2023-05-23T06:23:-0500",
"carVerticalDirection":"unknown",
"camera_info":{"serialNumber":"ZR8N6V4W20000AP","macAddress":"E430226AA345","cameraModel":"PNB-A9001LP"},
"channel":"1",
"recognitionZone":"2",
"imagesURI":["/home/setup/opensdk/html/WisenetRoadAI/images/images/20230523062228_66032/20230523062331_165987lp_08R0C8JE.png","/home/setup/opensdk/html/WisenetRoadAI/images/images/20230523062228_66032/20230523062331_165987.jpeg","/home/setup/opensdk/html/WisenetRoadAI/images/images/20230523062228_66032/20230523062331_165987lp_08R0C8JE.jpeg"],
"plateASCII":"08R0C8JE",
"plateUnicode":"\u0030\u0038\u0052\u0030\u0043\u0038\u004a\u0045",
"vehicle_info":{"brand":"Man","model":"","type":"TRUCK","color":"NONE","confidenceColor":"0.000000","confidenceMMR":"0.407773","coordinates":[744, 866, 1616, 1154]},
"sensorProviderID":"LPR_OFICINA",
"capture_timestamp":"1684823008245",
"frame_timestamp":"1684823008245"
}