{"packetCounter":"782",
"datetime":"20230523 055644000",
"plateText":"\u0048\u0030\u0030\u0038\u004a\u0045",
"plateCountry":"No Country",
"ISO3166":{"Alpha3":"No Country"},
"plateConfidence":"0.640697",
"carState":"new",
"geotag":{"lat": -12.58898,"lon": -76.56886},"imageType": "frame","carMoveDirection":"unknown",
"timeProcessing":"0",
"timeDetection":"20230523 055644000",
"plateCoordinates":[1424, 1732, 330, 72],
"plateCoordinatesRelative":[1424, 1732, 330, 72],
"carID":"19645",
"datetimezone":"2023-05-23T05:56:-0500",
"carVerticalDirection":"unknown",
"camera_info":{"serialNumber":"ZR8N6V4W20000AP","macAddress":"E430226AA345","cameraModel":"PNB-A9001LP"},
"channel":"1",
"recognitionZone":"2",
"imagesURI":["/home/setup/opensdk/html/WisenetRoadAI/images/images/20230523055242_724630/20230523055647_228208lp_H008JE.png","/home/setup/opensdk/html/WisenetRoadAI/images/images/20230523055242_724630/20230523055647_228208.jpeg","/home/setup/opensdk/html/WisenetRoadAI/images/images/20230523055242_724630/20230523055647_228208lp_H008JE.jpeg"],
"plateASCII":"H008JE",
"plateUnicode":"\u0048\u0030\u0030\u0038\u004a\u0045",
"vehicle_info":{"brand":"(None)","model":"","type":"UNDEFINED","color":"NONE","confidenceColor":"0.000000","confidenceMMR":"0.167230","coordinates":[928, 868, 1320, 1152]},
"sensorProviderID":"LPR_OFICINA",
"capture_timestamp":"1684821404807",
"frame_timestamp":"1684821404807"
}