{"packetCounter":"485",
"datetime":"20230523 160946000",
"plateText":"\u0043\u0048\u0047\u0037\u0031\u0034",
"plateCountry":"COL",
"ISO3166":{"Alpha3":"COL"},
"plateConfidence":"0.647061",
"carState":"new",
"geotag":{"lat": -12.58898,"lon": -76.56886},"imageType": "frame","carMoveDirection":"unknown",
"timeProcessing":"0",
"timeDetection":"20230523 160946000",
"plateCoordinates":[2264, 992, 414, 174],
"plateCoordinatesRelative":[2264, 992, 414, 174],
"carID":"21808",
"datetimezone":"2023-05-23T16:09:-0500",
"carVerticalDirection":"unknown",
"camera_info":{"serialNumber":"ZR8N6V4W20000AP","macAddress":"E430226AA345","cameraModel":"PNB-A9001LP"},
"channel":"1",
"recognitionZone":"1",
"imagesURI":["/home/setup/opensdk/html/WisenetRoadAI/images/images/20230523160231_111149/20230523160947_531149lp_CHG714.png","/home/setup/opensdk/html/WisenetRoadAI/images/images/20230523160231_111149/20230523160947_531149.jpeg","/home/setup/opensdk/html/WisenetRoadAI/images/images/20230523160231_111149/20230523160947_531149lp_CHG714.jpeg"],
"plateASCII":"CHG714",
"plateUnicode":"\u0043\u0048\u0047\u0037\u0031\u0034",
"vehicle_info":{"brand":"(None)","model":"","type":"UNDEFINED","color":"NONE","confidenceColor":"0.000000","confidenceMMR":"0.195004","coordinates":[1640, 0, 1656, 1688]},
"sensorProviderID":"LPR_OFICINA",
"capture_timestamp":"1684858186572",
"frame_timestamp":"1684858186572"
}