{"packetCounter":"5069",
"datetime":"20230708 163951000",
"plateText":"\u005a\u0055\u0047\u0031\u0033\u0032",
"plateCountry":"ARG",
"ISO3166":{"Alpha3":"ARG"},
"plateConfidence":"0.664448",
"carState":"new",
"geotag":{"lat": 0,"lon": 0},"imageType": "frame","carMoveDirection":"unknown",
"timeProcessing":"0",
"timeDetection":"20230708 163951000",
"plateCoordinates":[592, 282, 103, 44],
"plateCoordinatesRelative":[592, 282, 103, 44],
"carID":"10166",
"datetimezone":"2023-07-08T16:39:-0500",
"carVerticalDirection":"unknown",
"camera_info":{"serialNumber":"ZR8N6V4W200006M","macAddress":"E430226AA341","cameraModel":"PNB-A9001LP"},
"channel":"1",
"recognitionZone":"1",
"imagesURI":["/home/setup/opensdk/html/WisenetRoadAI/images/images/20230708144022_448050/20230708163952_498027lp_ZUG132.png","/home/setup/opensdk/html/WisenetRoadAI/images/images/20230708144022_448050/20230708163952_498027.jpeg","/home/setup/opensdk/html/WisenetRoadAI/images/images/20230708144022_448050/20230708163952_498027lp_ZUG132.jpeg"],
"plateASCII":"ZUG132",
"plateUnicode":"\u005a\u0055\u0047\u0031\u0033\u0032",
"vehicle_info":{"brand":"Mitsubishi","model":"Eclipse","type":"CAR","color":"GRAY","confidenceColor":"0.000000","confidenceMMR":"0.421324","coordinates":[436, 0, 408, 461]},
"sensorProviderID":"LPR_ALTO",
"capture_timestamp":"1688834391917",
"frame_timestamp":"1688834391917"
}