{"packetCounter":"3100",
"datetime":"20230705 193704000",
"plateText":"\u0037\u0055\u0032\u0036\u0035",
"plateCountry":"No Country",
"ISO3166":{"Alpha3":"No Country"},
"plateConfidence":"0.774750",
"carState":"new",
"geotag":{"lat": 0,"lon": 0},"imageType": "frame","carMoveDirection":"unknown",
"timeProcessing":"0",
"timeDetection":"20230705 193704000",
"plateCoordinates":[952, 294, 93, 48],
"plateCoordinatesRelative":[952, 294, 93, 48],
"carID":"8197",
"datetimezone":"2023-07-05T19:37:-0500",
"carVerticalDirection":"unknown",
"camera_info":{"serialNumber":"ZR8N6V4W200006M","macAddress":"E430226AA341","cameraModel":"PNB-A9001LP"},
"channel":"1",
"recognitionZone":"1",
"imagesURI":["/home/setup/opensdk/html/WisenetRoadAI/images/images/20230705193704_692686/20230705193704_692686lp_7U265.png","/home/setup/opensdk/html/WisenetRoadAI/images/images/20230705193704_692686/20230705193704_692686.jpeg","/home/setup/opensdk/html/WisenetRoadAI/images/images/20230705193704_692686/20230705193704_692686lp_7U265.jpeg"],
"plateASCII":"7U265",
"plateUnicode":"\u0037\u0055\u0032\u0036\u0035",
"vehicle_info":{"brand":"Toyota","model":"Camry","type":"CAR","color":"WHITE","confidenceColor":"0.000000","confidenceMMR":"0.460405","coordinates":[812, 0, 368, 489]},
"sensorProviderID":"LPR_ALTO",
"capture_timestamp":"1688585824085",
"frame_timestamp":"1688585824085"
}