{"packetCounter":"3003",
"datetime":"20230705 181534000",
"plateText":"\u0042\u0042\u0053\u0038\u0036\u0035",
"plateCountry":"PRY",
"ISO3166":{"Alpha3":"PRY"},
"plateConfidence":"0.713555",
"carState":"new",
"geotag":{"lat": 0,"lon": 0},"imageType": "frame","carMoveDirection":"unknown",
"timeProcessing":"0",
"timeDetection":"20230705 181534000",
"plateCoordinates":[1237, 271, 103, 33],
"plateCoordinatesRelative":[1237, 271, 103, 33],
"carID":"8100",
"datetimezone":"2023-07-05T18:15:-0500",
"carVerticalDirection":"unknown",
"camera_info":{"serialNumber":"ZR8N6V4W200006M","macAddress":"E430226AA341","cameraModel":"PNB-A9001LP"},
"channel":"1",
"recognitionZone":"1",
"imagesURI":["/home/setup/opensdk/html/WisenetRoadAI/images/images/20230705181324_632900/20230705181534_880268lp_BBS865.png","/home/setup/opensdk/html/WisenetRoadAI/images/images/20230705181324_632900/20230705181534_880268.jpeg","/home/setup/opensdk/html/WisenetRoadAI/images/images/20230705181324_632900/20230705181534_880268lp_BBS865.jpeg"],
"plateASCII":"BBS865",
"plateUnicode":"\u0042\u0042\u0053\u0038\u0036\u0035",
"vehicle_info":{"brand":"Ford","model":"Explorer","type":"SUV","color":"WHITE","confidenceColor":"0.000000","confidenceMMR":"0.395325","coordinates":[1080, 0, 408, 404]},
"sensorProviderID":"LPR_ALTO",
"capture_timestamp":"1688580934511",
"frame_timestamp":"1688580934511"
}