{"packetCounter":"664",
"datetime":"20230523 163652000",
"plateText":"\u0047\u004f\u004b\u0044\u0039\u0049\u0045\u004b\u0048\u0049\u004b",
"plateCountry":"No Country",
"ISO3166":{"Alpha3":"No Country"},
"plateConfidence":"0.629426",
"carState":"new",
"geotag":{"lat": -12.58898,"lon": -76.56886},"imageType": "frame","carMoveDirection":"unknown",
"timeProcessing":"0",
"timeDetection":"20230523 163652000",
"plateCoordinates":[3146, 1342, 353, 92],
"plateCoordinatesRelative":[3146, 1342, 353, 92],
"carID":"22145",
"datetimezone":"2023-05-23T16:36:-0500",
"carVerticalDirection":"unknown",
"camera_info":{"serialNumber":"ZR8N6V4W20000AP","macAddress":"E430226AA345","cameraModel":"PNB-A9001LP"},
"channel":"1",
"recognitionZone":"1",
"imagesURI":["/home/setup/opensdk/html/WisenetRoadAI/images/images/20230523162455_479422/20230523163653_318972lp_GOKD9IEKHIK.png","/home/setup/opensdk/html/WisenetRoadAI/images/images/20230523162455_479422/20230523163653_318972.jpeg","/home/setup/opensdk/html/WisenetRoadAI/images/images/20230523162455_479422/20230523163653_318972lp_GOKD9IEKHIK.jpeg"],
"plateASCII":"GOKD9IEKHIK",
"plateUnicode":"\u0047\u004f\u004b\u0044\u0039\u0049\u0045\u004b\u0048\u0049\u004b",
"vehicle_info":{"brand":"Freightliner","model":"MT","type":"LCV","color":"NONE","confidenceColor":"0.000000","confidenceMMR":"0.403749","coordinates":[2616, 238, 1220, 1475]},
"sensorProviderID":"LPR_OFICINA",
"capture_timestamp":"1684859812041",
"frame_timestamp":"1684859812041"
}