{"packetCounter":"4973",
"datetime":"20230708 140643000",
"plateText":"\u0034\u0041\u0046\u0030\u0031",
"plateCountry":"No Country",
"ISO3166":{"Alpha3":"No Country"},
"plateConfidence":"0.760552",
"carState":"new",
"geotag":{"lat": 0,"lon": 0},"imageType": "frame","carMoveDirection":"unknown",
"timeProcessing":"0",
"timeDetection":"20230708 140643000",
"plateCoordinates":[1254, 448, 134, 124],
"plateCoordinatesRelative":[1254, 448, 134, 124],
"carID":"10070",
"datetimezone":"2023-07-08T14:06:-0500",
"carVerticalDirection":"unknown",
"camera_info":{"serialNumber":"ZR8N6V4W200006M","macAddress":"E430226AA341","cameraModel":"PNB-A9001LP"},
"channel":"1",
"recognitionZone":"1",
"imagesURI":["/home/setup/opensdk/html/WisenetRoadAI/images/images/20230708121311_712879/20230708140650_691778lp_4AF01.png","/home/setup/opensdk/html/WisenetRoadAI/images/images/20230708121311_712879/20230708140650_691778.jpeg","/home/setup/opensdk/html/WisenetRoadAI/images/images/20230708121311_712879/20230708140650_691778lp_4AF01.jpeg"],
"plateASCII":"4AF01",
"plateUnicode":"\u0034\u0041\u0046\u0030\u0031",
"vehicle_info":{"brand":"Undefined","model":"","type":"BUS","color":"WHITE","confidenceColor":"0.000000","confidenceMMR":"0.708441","coordinates":[1052, 0, 536, 944]},
"sensorProviderID":"LPR_ALTO",
"capture_timestamp":"1688825203738",
"frame_timestamp":"1688825203738"
}