{"packetCounter":"1135",
"datetime":"20230523 194611000",
"plateText":"\u0038\u0039\u0035\u0032\u0044\u0044",
"plateCountry":"No Country",
"ISO3166":{"Alpha3":"No Country"},
"plateConfidence":"0.644374",
"carState":"new",
"geotag":{"lat": -12.58898,"lon": -76.56886},"imageType": "frame","carMoveDirection":"unknown",
"timeProcessing":"0",
"timeDetection":"20230523 194611000",
"plateCoordinates":[930, 299, 241, 66],
"plateCoordinatesRelative":[930, 299, 241, 66],
"carID":"23673",
"datetimezone":"2023-05-23T19:46:-0500",
"carVerticalDirection":"unknown",
"camera_info":{"serialNumber":"ZR8N6V4W20000AP","macAddress":"E430226AA345","cameraModel":"PNB-A9001LP"},
"channel":"1",
"recognitionZone":"1",
"imagesURI":["/home/setup/opensdk/html/WisenetRoadAI/images/images/20230523193815_152309/20230523194612_14749lp_8952DD.png","/home/setup/opensdk/html/WisenetRoadAI/images/images/20230523193815_152309/20230523194612_14749.jpeg","/home/setup/opensdk/html/WisenetRoadAI/images/images/20230523193815_152309/20230523194612_14749lp_8952DD.jpeg"],
"plateASCII":"8952DD",
"plateUnicode":"\u0038\u0039\u0035\u0032\u0044\u0044",
"vehicle_info":{"brand":"Chevrolet","model":"Express","type":"VAN","color":"NONE","confidenceColor":"0.000000","confidenceMMR":"0.526774","coordinates":[568, 0, 960, 563]},
"sensorProviderID":"LPR_OFICINA",
"capture_timestamp":"1684871171523",
"frame_timestamp":"1684871171523"
}