{"packetCounter":"142",
"datetime":"20230523 153040000",
"plateText":"\u004f\u0053\u004c\u0033\u0030\u0036\u0035",
"plateCountry":"BRA",
"ISO3166":{"Alpha3":"BRA"},
"plateConfidence":"0.655911",
"carState":"new",
"geotag":{"lat": -12.58898,"lon": -76.56886},"imageType": "frame","carMoveDirection":"unknown",
"timeProcessing":"0",
"timeDetection":"20230523 153040000",
"plateCoordinates":[3097, 882, 127, 48],
"plateCoordinatesRelative":[3097, 882, 127, 48],
"carID":"21163",
"datetimezone":"2023-05-23T15:30:-0500",
"carVerticalDirection":"unknown",
"camera_info":{"serialNumber":"ZR8N6V4W20000AP","macAddress":"E430226AA345","cameraModel":"PNB-A9001LP"},
"channel":"1",
"recognitionZone":"1",
"imagesURI":["/home/setup/opensdk/html/WisenetRoadAI/images/images/20230523151854_474635/20230523153042_361008lp_OSL3065.png","/home/setup/opensdk/html/WisenetRoadAI/images/images/20230523151854_474635/20230523153042_361008.jpeg","/home/setup/opensdk/html/WisenetRoadAI/images/images/20230523151854_474635/20230523153042_361008lp_OSL3065.jpeg"],
"plateASCII":"OSL3065",
"plateUnicode":"\u004f\u0053\u004c\u0033\u0030\u0036\u0035",
"vehicle_info":{"brand":"(None)","model":"","type":"UNDEFINED","color":"NONE","confidenceColor":"0.000000","confidenceMMR":"0.256377","coordinates":[2904, 306, 504, 772]},
"sensorProviderID":"LPR_OFICINA",
"capture_timestamp":"1684855840642",
"frame_timestamp":"1684855840642"
}