{"packetCounter":"365",
"datetime":"20230523 155813000",
"plateText":"\u004f\u0031\u0049\u0038\u004d\u0049\u0049\u0036\u0043\u004f\u0030\u004f",
"plateCountry":"No Country",
"ISO3166":{"Alpha3":"No Country"},
"plateConfidence":"0.640837",
"carState":"new",
"geotag":{"lat": -12.58898,"lon": -76.56886},"imageType": "frame","carMoveDirection":"unknown",
"timeProcessing":"0",
"timeDetection":"20230523 155813000",
"plateCoordinates":[3144, 591, 283, 62],
"plateCoordinatesRelative":[3144, 591, 283, 62],
"carID":"21578",
"datetimezone":"2023-05-23T15:58:-0500",
"carVerticalDirection":"unknown",
"camera_info":{"serialNumber":"ZR8N6V4W20000AP","macAddress":"E430226AA345","cameraModel":"PNB-A9001LP"},
"channel":"1",
"recognitionZone":"1",
"imagesURI":["/home/setup/opensdk/html/WisenetRoadAI/images/images/20230523155757_147098/20230523155814_890414lp_O1I8MII6CO0O.png","/home/setup/opensdk/html/WisenetRoadAI/images/images/20230523155757_147098/20230523155814_890414.jpeg","/home/setup/opensdk/html/WisenetRoadAI/images/images/20230523155757_147098/20230523155814_890414lp_O1I8MII6CO0O.jpeg"],
"plateASCII":"O1I8MII6CO0O",
"plateUnicode":"\u004f\u0031\u0049\u0038\u004d\u0049\u0049\u0036\u0043\u004f\u0030\u004f",
"vehicle_info":{"brand":"Volvo","model":"","type":"TRUCK","color":"NONE","confidenceColor":"0.000000","confidenceMMR":"0.716831","coordinates":[2720, 0, 1120, 838]},
"sensorProviderID":"LPR_OFICINA",
"capture_timestamp":"1684857493781",
"frame_timestamp":"1684857493781"
}