{"packetCounter":"3350",
"datetime":"20230706 003841000",
"plateText":"\u0050\u0049\u0032\u0035\u0030",
"plateCountry":"CHL",
"ISO3166":{"Alpha3":"CHL"},
"plateConfidence":"0.665524",
"carState":"new",
"geotag":{"lat": 0,"lon": 0},"imageType": "frame","carMoveDirection":"unknown",
"timeProcessing":"0",
"timeDetection":"20230706 003841000",
"plateCoordinates":[1133, 267, 85, 28],
"plateCoordinatesRelative":[1133, 267, 85, 28],
"carID":"8447",
"datetimezone":"2023-07-06T00:38:-0500",
"carVerticalDirection":"unknown",
"camera_info":{"serialNumber":"ZR8N6V4W200006M","macAddress":"E430226AA341","cameraModel":"PNB-A9001LP"},
"channel":"1",
"recognitionZone":"1",
"imagesURI":["/home/setup/opensdk/html/WisenetRoadAI/images/images/20230705232327_137098/20230706003842_295318lp_PI250.png","/home/setup/opensdk/html/WisenetRoadAI/images/images/20230705232327_137098/20230706003842_295318.jpeg","/home/setup/opensdk/html/WisenetRoadAI/images/images/20230705232327_137098/20230706003842_295318lp_PI250.jpeg"],
"plateASCII":"PI250",
"plateUnicode":"\u0050\u0049\u0032\u0035\u0030",
"vehicle_info":{"brand":"Citroen","model":"Xsara","type":"CAR","color":"NONE","confidenceColor":"0.000000","confidenceMMR":"0.449429","coordinates":[1004, 0, 336, 381]},
"sensorProviderID":"LPR_ALTO",
"capture_timestamp":"1688603921942",
"frame_timestamp":"1688603921942"
}