{"packetCounter":"4234",
"datetime":"20230707 142034000",
"plateText":"\u0050\u005a\u0058\u0036\u0033\u0038",
"plateCountry":"PRY",
"ISO3166":{"Alpha3":"PRY"},
"plateConfidence":"0.701186",
"carState":"new",
"geotag":{"lat": 0,"lon": 0},"imageType": "frame","carMoveDirection":"unknown",
"timeProcessing":"0",
"timeDetection":"20230707 142034000",
"plateCoordinates":[1052, 258, 106, 42],
"plateCoordinatesRelative":[1052, 258, 106, 42],
"carID":"9331",
"datetimezone":"2023-07-07T14:20:-0500",
"carVerticalDirection":"unknown",
"camera_info":{"serialNumber":"ZR8N6V4W200006M","macAddress":"E430226AA341","cameraModel":"PNB-A9001LP"},
"channel":"1",
"recognitionZone":"1",
"imagesURI":["/home/setup/opensdk/html/WisenetRoadAI/images/images/20230707134125_871606/20230707142034_863835lp_PZX638.png","/home/setup/opensdk/html/WisenetRoadAI/images/images/20230707134125_871606/20230707142034_863835.jpeg","/home/setup/opensdk/html/WisenetRoadAI/images/images/20230707134125_871606/20230707142034_863835lp_PZX638.jpeg"],
"plateASCII":"PZX638",
"plateUnicode":"\u0050\u005a\u0058\u0036\u0033\u0038",
"vehicle_info":{"brand":"Volkswagen","model":"Transporter","type":"VAN","color":"WHITE","confidenceColor":"0.000000","confidenceMMR":"0.549500","coordinates":[892, 0, 424, 426]},
"sensorProviderID":"LPR_ALTO",
"capture_timestamp":"1688739634401",
"frame_timestamp":"1688739634401"
}