{"ISO3166":{"Alpha3":"PER"},"camera_info":{"cameraModel":"PNB-A9001LP","macAddress":"E430226AA341","serialNumber":"ZR8N6V4W200006M"},"capture_timestamp":1689274017199,"carID":12821,"carMoveDirection":"unknown","carState":"new","carVerticalDirection":"unknown","channel":"1","datetime":"20230713 184657000","datetimezone":"2023-07-13T18:46:-0500","frame_timestamp":1689274017199,"geotag":{"lat":0.0,"lon":0.0},"imageType":"frame","imagesURI":["/home/setup/opensdk/html/WisenetRoadAI/images/images/20230713182728_944191/20230713184657_737411lp_P3N314.png","/home/setup/opensdk/html/WisenetRoadAI/images/images/20230713182728_944191/20230713184657_737411.jpeg","/home/setup/opensdk/html/WisenetRoadAI/images/images/20230713182728_944191/20230713184657_737411lp_P3N314.jpeg"],"packetCounter":0,"plateASCII":"P3N314","plateConfidence":0.6978662014007568,"plateCoordinates":[4144,3640,596,216],"plateCoordinatesRelative":[4144,3640,596,216],"plateCountry":"PER","plateText":"\\u0050\\u0033\\u004e\\u0033\\u0031\\u0034","plateUnicode":"\\u0050\\u0033\\u004e\\u0033\\u0031\\u0034","recognitionZone":1,"sensorProviderID":"LPR_ALTO","timeDetection":1689274017199,"timeProcessing":0,"vehicle_info":{"brand":"","color":"","confidenceColor":0.0,"confidenceMMR":0.0,"coordinates":[1624,524,1192,1636],"model":"","type":""}}